causalfe/__init__.py
causalfe/did/__init__.py
causalfe/did/staggered.py
causalfe/forest/__init__.py
causalfe/forest/cffe_forest.py
causalfe/forest/residuals.py
causalfe/forest/splitting.py
causalfe/forest/tree.py
causalfe/inference/__init__.py
causalfe/inference/cluster_robust.py
causalfe/inference/half_sample.py
causalfe/simulations/__init__.py
causalfe/simulations/did_dgp.py
causalfe/utils/__init__.py
causalfe/utils/checks.py
causalfe/utils/validation.py
causalfe-0.2.0.dist-info/licenses/LICENSE
causalfe-0.2.0.dist-info/METADATA
causalfe-0.2.0.dist-info/WHEEL
causalfe-0.2.0.dist-info/top_level.txt
causalfe-0.2.0.dist-info/RECORD
