Metadata-Version: 2.4
Name: causalfe
Version: 0.2.0
Summary: Causal Forests with Fixed Effects for Panel and Difference-in-Differences Settings
Author: Harry Aytug
Author-email: Harry Aytug <haytug@gmail.com>
License: MIT
Project-URL: Homepage, https://github.com/haytug/causalfe
Project-URL: Documentation, https://github.com/haytug/causalfe#readme
Project-URL: Repository, https://github.com/haytug/causalfe
Project-URL: Issues, https://github.com/haytug/causalfe/issues
Project-URL: Original Paper, https://www.cpb.nl/en/publication/causal-forests-with-fixed-effects-for-treatment-effect-heterogeneity-in-difference-in-differences
Keywords: causal inference,causal forest,fixed effects,difference-in-differences,heterogeneous treatment effects,panel data,econometrics
Classifier: Development Status :: 4 - Beta
Classifier: Intended Audience :: Science/Research
Classifier: License :: OSI Approved :: MIT License
Classifier: Operating System :: OS Independent
Classifier: Programming Language :: Python :: 3
Classifier: Programming Language :: Python :: 3.9
Classifier: Programming Language :: Python :: 3.10
Classifier: Programming Language :: Python :: 3.11
Classifier: Programming Language :: Python :: 3.12
Classifier: Topic :: Scientific/Engineering :: Artificial Intelligence
Classifier: Topic :: Scientific/Engineering :: Mathematics
Requires-Python: >=3.8
License-File: LICENSE
Requires-Dist: numpy>=1.20
Requires-Dist: scipy>=1.7
Provides-Extra: dev
Requires-Dist: pytest>=7.0; extra == "dev"
Requires-Dist: pytest-cov; extra == "dev"
Requires-Dist: black; extra == "dev"
Requires-Dist: ruff; extra == "dev"
Provides-Extra: compare
Requires-Dist: econml>=0.14; extra == "compare"
Requires-Dist: scikit-learn>=1.0; extra == "compare"
Provides-Extra: all
Requires-Dist: causalfe[compare,dev]; extra == "all"
Requires-Dist: matplotlib>=3.5; extra == "all"
Dynamic: license-file
Dynamic: requires-python
